[{"team1": "Alabama", "team2": "Western Kentucky", "team1Elo": 1854, "team2Elo": 1466.0, "isHome": 1, "winner": 1, "week": 1}, {"team1": "Alabama", "team2": "South Florida", "team1Elo": 1997, "team2Elo": 1442.0, "isHome": 1, "winner": 1, "week": 2}, {"team1": "Alabama", "team2": "Wisconsin", "team1Elo": 2006.0, "team2Elo": 1593, "isHome": 0, "winner": 1, "week": 3}, {"team1": "Alabama", "team2": "Georgia", "team1Elo": 2046, "team2Elo": 2046.0, "isHome": 1, "winner": 1, "week": 5}, {"team1": "Alabama", "team2": "Vanderbilt", "team1Elo": 2056.0, "team2Elo": 1317, "isHome": 0, "winner": 0, "week": 6}, {"team1": "Alabama", "team2": "South Carolina", "team1Elo": 2014, "team2Elo": 1654.0, "isHome": 1, "winner": 1, "week": 7}, {"team1": "Alabama", "team2": "Tennessee", "team1Elo": 2010.0, "team2Elo": 1936, "isHome": 0, "winner": 0, "week": 8}, {"team1": "Alabama", "team2": "Missouri", "team1Elo": 1996, "team2Elo": 1735.0, "isHome": 1, "winner": 1, "week": 9}, {"team1": "Alabama", "team2": "LSU", "team1Elo": 2058.0, "team2Elo": 1855, "isHome": 0, "winner": 1, "week": 11}, {"team1": "Alabama", "team2": "Mercer", "team1Elo": 2130, "team2Elo": NaN, "isHome": 1, "winner": 1, "week": 12}, {"team1": "Alabama", "team2": "Oklahoma", "team1Elo": 2113.0, "team2Elo": 1678, "isHome": 0, "winner": 0, "week": 13}, {"team1": "Alabama", "team2": "Auburn", "team1Elo": 2011, "team2Elo": 1607.0, "isHome": 1, "winner": 1, "week": 14}, {"team1": "Alabama", "team2": "Michigan", "team1Elo": 2007.0, "team2Elo": 1888, "isHome": 0, "winner": 0, "week": 1}]