{"firstDowns": 128, "firstDownsOpponent": 105, "fourthDownConversions": 7, "fourthDownConversionsOpponent": 3, "fourthDowns": 10, "fourthDownsOpponent": 7, "fumblesLost": 3, "fumblesLostOpponent": 3, "fumblesRecovered": 3, "fumblesRecoveredOpponent": 3, "games": 5, "interceptions": 7, "interceptionsOpponent": 1, "interceptionTDs": 0, "interceptionTDsOpponent": 2, "interceptionYards": 21, "interceptionYardsOpponent": 160, "kickReturns": 14, "kickReturnsOpponent": 12, "kickReturnTDs": 0, "kickReturnTDsOpponent": 0, "kickReturnYards": 260, "kickReturnYardsOpponent": 204, "netPassingYards": 1523, "netPassingYardsOpponent": 1091, "passAttempts": 210, "passAttemptsOpponent": 125, "passCompletions": 119, "passCompletionsOpponent": 85, "passesIntercepted": 1, "passesInterceptedOpponent": 7, "passingTDs": 8, "passingTDsOpponent": 11, "penalties": 39, "penaltiesOpponent": 38, "penaltyYards": 400, "penaltyYardsOpponent": 346, "possessionTime": 9429, "possessionTimeOpponent": 8506, "puntReturns": 1, "puntReturnsOpponent": 13, "puntReturnTDs": 0, "puntReturnTDsOpponent": 0, "puntReturnYards": 0, "puntReturnYardsOpponent": 139, "rushingAttempts": 163, "rushingAttemptsOpponent": 186, "rushingTDs": 8, "rushingTDsOpponent": 13, "rushingYards": 703, "rushingYardsOpponent": 1089, "sacks": 8, "sacksOpponent": 7, "tacklesForLoss": 20, "tacklesForLossOpponent": 29, "thirdDownConversions": 23, "thirdDownConversionsOpponent": 25, "thirdDowns": 67, "thirdDownsOpponent": 57, "totalYards": 2226, "totalYardsOpponent": 2180, "turnovers": 10, "turnoversOpponent": 4}