[{"team1": "Arizona State", "team2": "Wyoming", "team1Elo": 1355, "team2Elo": 1496, "isHome": 1, "winner": 1, "week": 1}, {"team1": "Arizona State", "team2": "Mississippi State", "team1Elo": 1497, "team2Elo": 1447, "isHome": 1, "winner": 1, "week": 2}, {"team1": "Arizona State", "team2": "Texas State", "team1Elo": 1504, "team2Elo": 1545, "isHome": 0, "winner": 1, "week": 3}, {"team1": "Arizona State", "team2": "Texas Tech", "team1Elo": 1511, "team2Elo": 1623, "isHome": 0, "winner": 0, "week": 4}, {"team1": "Arizona State", "team2": "Kansas", "team1Elo": 1506, "team2Elo": 1575, "isHome": 1, "winner": 1, "week": 6}, {"team1": "Arizona State", "team2": "Utah", "team1Elo": 1511, "team2Elo": 1607, "isHome": 1, "winner": 1, "week": 7}, {"team1": "Arizona State", "team2": "Cincinnati", "team1Elo": 1529, "team2Elo": 1538, "isHome": 0, "winner": 0, "week": 8}, {"team1": "Arizona State", "team2": "Oklahoma State", "team1Elo": 1513, "team2Elo": 1477, "isHome": 0, "winner": 1, "week": 10}, {"team1": "Arizona State", "team2": "UCF", "team1Elo": 1563, "team2Elo": 1625, "isHome": 1, "winner": 1, "week": 11}, {"team1": "Arizona State", "team2": "Kansas State", "team1Elo": 1568, "team2Elo": 1771, "isHome": 0, "winner": 1, "week": 12}, {"team1": "Arizona State", "team2": "BYU", "team1Elo": 1608, "team2Elo": 1667, "isHome": 1, "winner": 1, "week": 13}, {"team1": "Arizona State", "team2": "Arizona", "team1Elo": 1615, "team2Elo": 1404, "isHome": 0, "winner": 1, "week": 14}, {"team1": "Arizona State", "team2": "Iowa State", "team1Elo": 1712, "team2Elo": 1751, "isHome": 1, "winner": 1, "week": 15}, {"team1": "Arizona State", "team2": "Texas", "team1Elo": 1792, "team2Elo": 2065, "isHome": 1, "winner": 0, "week": 1}]