{"firstDowns": 22, "firstDownsOpponent": 18, "fourthDownConversions": 1, "fourthDownConversionsOpponent": 4, "fourthDowns": 1, "fourthDownsOpponent": 5, "fumblesLost": 0, "fumblesLostOpponent": 0, "fumblesRecovered": 0, "fumblesRecoveredOpponent": 0, "games": 1, "interceptions": 0, "interceptionsOpponent": 0, "kickReturns": 2, "kickReturnsOpponent": 4, "kickReturnTDs": 1, "kickReturnTDsOpponent": 0, "kickReturnYards": 123, "kickReturnYardsOpponent": 71, "netPassingYards": 170, "netPassingYardsOpponent": 219, "passAttempts": 23, "passAttemptsOpponent": 23, "passCompletions": 16, "passCompletionsOpponent": 14, "passingTDs": 0, "passingTDsOpponent": 2, "penalties": 7, "penaltiesOpponent": 6, "penaltyYards": 85, "penaltyYardsOpponent": 40, "possessionTime": 1643, "possessionTimeOpponent": 1957, "puntReturns": 2, "puntReturnTDs": 0, "puntReturnYards": 16, "rushingAttempts": 33, "rushingAttemptsOpponent": 42, "rushingTDs": 5, "rushingTDsOpponent": 0, "rushingYards": 305, "rushingYardsOpponent": 182, "sacks": 5, "sacksOpponent": 0, "tacklesForLoss": 6, "tacklesForLossOpponent": 2, "thirdDownConversions": 5, "thirdDownConversionsOpponent": 4, "thirdDowns": 9, "thirdDownsOpponent": 16, "totalYards": 475, "totalYardsOpponent": 401, "turnovers": 0, "turnoversOpponent": 0}