{"firstDowns": 17, "firstDownsOpponent": 11, "fourthDownConversions": 0, "fourthDownConversionsOpponent": 1, "fourthDowns": 2, "fourthDownsOpponent": 2, "fumblesLost": 0, "fumblesLostOpponent": 0, "fumblesRecovered": 0, "fumblesRecoveredOpponent": 0, "games": 1, "interceptions": 1, "interceptionsOpponent": 0, "interceptionTDsOpponent": 0, "interceptionYardsOpponent": 0, "kickReturnsOpponent": 2, "kickReturnTDsOpponent": 0, "kickReturnYardsOpponent": 33, "netPassingYards": 291, "netPassingYardsOpponent": 110, "passAttempts": 40, "passAttemptsOpponent": 24, "passCompletions": 26, "passCompletionsOpponent": 16, "passesInterceptedOpponent": 1, "passingTDs": 2, "passingTDsOpponent": 0, "penalties": 0, "penaltiesOpponent": 5, "penaltyYards": 0, "penaltyYardsOpponent": 30, "possessionTime": 1610, "possessionTimeOpponent": 1990, "puntReturns": 3, "puntReturnsOpponent": 1, "puntReturnTDs": 0, "puntReturnTDsOpponent": 0, "puntReturnYards": 30, "puntReturnYardsOpponent": -3, "rushingAttempts": 27, "rushingAttemptsOpponent": 36, "rushingTDs": 1, "rushingTDsOpponent": 0, "rushingYards": 59, "rushingYardsOpponent": 30, "sacks": 8, "sacksOpponent": 0, "tacklesForLoss": 16, "tacklesForLossOpponent": 6, "thirdDownConversions": 5, "thirdDownConversionsOpponent": 3, "thirdDowns": 12, "thirdDownsOpponent": 15, "totalYards": 350, "totalYardsOpponent": 140, "turnovers": 1, "turnoversOpponent": 0}