{"firstDowns": 128, "firstDownsOpponent": 194, "fourthDownConversions": 18, "fourthDownConversionsOpponent": 9, "fourthDowns": 29, "fourthDownsOpponent": 14, "fumblesLost": 4, "fumblesLostOpponent": 1, "fumblesRecovered": 1, "fumblesRecoveredOpponent": 4, "games": 9, "interceptions": 11, "interceptionsOpponent": 2, "interceptionTDs": 0, "interceptionTDsOpponent": 2, "interceptionYards": 12, "interceptionYardsOpponent": 253, "kickReturns": 17, "kickReturnsOpponent": 7, "kickReturnTDs": 1, "kickReturnTDsOpponent": 0, "kickReturnYards": 405, "kickReturnYardsOpponent": 178, "netPassingYards": 1696, "netPassingYardsOpponent": 1812, "passAttempts": 278, "passAttemptsOpponent": 242, "passCompletions": 138, "passCompletionsOpponent": 151, "passesIntercepted": 2, "passesInterceptedOpponent": 11, "passingTDs": 8, "passingTDsOpponent": 11, "penalties": 57, "penaltiesOpponent": 44, "penaltyYards": 474, "penaltyYardsOpponent": 391, "possessionTime": 13996, "possessionTimeOpponent": 18333, "puntReturns": 9, "puntReturnsOpponent": 20, "puntReturnTDs": 0, "puntReturnTDsOpponent": 0, "puntReturnYards": 7, "puntReturnYardsOpponent": 114, "rushingAttempts": 256, "rushingAttemptsOpponent": 373, "rushingTDs": 5, "rushingTDsOpponent": 15, "rushingYards": 695, "rushingYardsOpponent": 1749, "sacks": 19, "sacksOpponent": 27, "tacklesForLoss": 51, "tacklesForLossOpponent": 58, "thirdDownConversions": 31, "thirdDownConversionsOpponent": 62, "thirdDowns": 120, "thirdDownsOpponent": 133, "totalYards": 2391, "totalYardsOpponent": 3561, "turnovers": 15, "turnoversOpponent": 3}