{"firstDowns": 165, "firstDownsOpponent": 151, "fourthDownConversions": 6, "fourthDownConversionsOpponent": 10, "fourthDowns": 13, "fourthDownsOpponent": 14, "fumblesLost": 3, "fumblesLostOpponent": 4, "fumblesRecovered": 4, "fumblesRecoveredOpponent": 3, "games": 8, "interceptions": 8, "interceptionsOpponent": 4, "interceptionTDs": 0, "interceptionTDsOpponent": 0, "interceptionYards": 12, "interceptionYardsOpponent": 91, "kickReturns": 17, "kickReturnsOpponent": 16, "kickReturnTDs": 0, "kickReturnTDsOpponent": 0, "kickReturnYards": 266, "kickReturnYardsOpponent": 269, "netPassingYards": 1946, "netPassingYardsOpponent": 1768, "passAttempts": 298, "passAttemptsOpponent": 244, "passCompletions": 180, "passCompletionsOpponent": 160, "passesIntercepted": 4, "passesInterceptedOpponent": 8, "passingTDs": 13, "passingTDsOpponent": 12, "penalties": 64, "penaltiesOpponent": 61, "penaltyYards": 587, "penaltyYardsOpponent": 580, "possessionTime": 14174, "possessionTimeOpponent": 14626, "puntReturns": 8, "puntReturnsOpponent": 10, "puntReturnTDs": 1, "puntReturnTDsOpponent": 0, "puntReturnYards": 99, "puntReturnYardsOpponent": 76, "rushingAttempts": 212, "rushingAttemptsOpponent": 260, "rushingTDs": 7, "rushingTDsOpponent": 10, "rushingYards": 841, "rushingYardsOpponent": 1068, "sacks": 18, "sacksOpponent": 28, "tacklesForLoss": 48, "tacklesForLossOpponent": 47, "thirdDownConversions": 36, "thirdDownConversionsOpponent": 46, "thirdDowns": 99, "thirdDownsOpponent": 110, "totalYards": 2787, "totalYardsOpponent": 2836, "turnovers": 11, "turnoversOpponent": 8}