{"firstDowns": 95, "firstDownsOpponent": 114, "fourthDownConversions": 7, "fourthDownConversionsOpponent": 2, "fourthDowns": 8, "fourthDownsOpponent": 3, "fumblesLost": 4, "fumblesLostOpponent": 2, "fumblesRecovered": 2, "fumblesRecoveredOpponent": 4, "games": 6, "interceptions": 8, "interceptionsOpponent": 6, "interceptionTDs": 2, "interceptionTDsOpponent": 0, "interceptionYards": 133, "interceptionYardsOpponent": 80, "kickReturns": 11, "kickReturnsOpponent": 4, "kickReturnTDs": 0, "kickReturnTDsOpponent": 0, "kickReturnYards": 197, "kickReturnYardsOpponent": 63, "netPassingYards": 690, "netPassingYardsOpponent": 1559, "passAttempts": 133, "passAttemptsOpponent": 241, "passCompletions": 81, "passCompletionsOpponent": 150, "passesIntercepted": 6, "passesInterceptedOpponent": 8, "passingTDs": 6, "passingTDsOpponent": 12, "penalties": 29, "penaltiesOpponent": 28, "penaltyYards": 288, "penaltyYardsOpponent": 192, "possessionTime": 11408, "possessionTimeOpponent": 10192, "puntReturns": 9, "puntReturnsOpponent": 6, "puntReturnTDs": 0, "puntReturnTDsOpponent": 0, "puntReturnYards": 97, "puntReturnYardsOpponent": 104, "rushingAttempts": 226, "rushingAttemptsOpponent": 160, "rushingTDs": 9, "rushingTDsOpponent": 4, "rushingYards": 1150, "rushingYardsOpponent": 458, "sacks": 17, "sacksOpponent": 8, "tacklesForLoss": 36, "tacklesForLossOpponent": 27, "thirdDownConversions": 30, "thirdDownConversionsOpponent": 37, "thirdDowns": 77, "thirdDownsOpponent": 91, "totalYards": 1840, "totalYardsOpponent": 2017, "turnovers": 12, "turnoversOpponent": 8}