{"firstDowns": 207, "firstDownsOpponent": 173, "fourthDownConversions": 3, "fourthDownConversionsOpponent": 8, "fourthDowns": 6, "fourthDownsOpponent": 15, "fumblesLost": 8, "fumblesLostOpponent": 4, "fumblesRecovered": 4, "fumblesRecoveredOpponent": 8, "games": 10, "interceptions": 9, "interceptionsOpponent": 9, "interceptionTDs": 1, "interceptionTDsOpponent": 1, "interceptionYards": 45, "interceptionYardsOpponent": 64, "kickReturns": 21, "kickReturnsOpponent": 21, "kickReturnTDs": 1, "kickReturnTDsOpponent": 0, "kickReturnYards": 463, "kickReturnYardsOpponent": 391, "netPassingYards": 1871, "netPassingYardsOpponent": 1977, "passAttempts": 256, "passAttemptsOpponent": 302, "passCompletions": 158, "passCompletionsOpponent": 187, "passesIntercepted": 9, "passesInterceptedOpponent": 9, "passingTDs": 8, "passingTDsOpponent": 11, "penalties": 53, "penaltiesOpponent": 60, "penaltyYards": 444, "penaltyYardsOpponent": 526, "possessionTime": 18668, "possessionTimeOpponent": 17332, "puntReturns": 12, "puntReturnsOpponent": 17, "puntReturnTDs": 1, "puntReturnTDsOpponent": 0, "puntReturnYards": 128, "puntReturnYardsOpponent": 125, "rushingAttempts": 385, "rushingAttemptsOpponent": 320, "rushingTDs": 24, "rushingTDsOpponent": 11, "rushingYards": 2017, "rushingYardsOpponent": 1100, "sacks": 23, "sacksOpponent": 16, "tacklesForLoss": 68, "tacklesForLossOpponent": 53, "thirdDownConversions": 56, "thirdDownConversionsOpponent": 49, "thirdDowns": 123, "thirdDownsOpponent": 139, "totalYards": 3888, "totalYardsOpponent": 3077, "turnovers": 17, "turnoversOpponent": 13}