{"firstDowns": 130, "firstDownsOpponent": 63, "fourthDownConversions": 4, "fourthDownConversionsOpponent": 5, "fourthDowns": 7, "fourthDownsOpponent": 10, "fumblesLost": 1, "fumblesLostOpponent": 3, "fumblesRecovered": 3, "fumblesRecoveredOpponent": 1, "games": 4, "interceptions": 2, "interceptionsOpponent": 4, "interceptionTDs": 0, "interceptionTDsOpponent": 0, "interceptionYards": 5, "interceptionYardsOpponent": -3, "kickReturns": 3, "kickReturnsOpponent": 5, "kickReturnTDs": 0, "kickReturnTDsOpponent": 0, "kickReturnYards": 50, "kickReturnYardsOpponent": 76, "netPassingYards": 1691, "netPassingYardsOpponent": 818, "passAttempts": 143, "passAttemptsOpponent": 149, "passCompletions": 105, "passCompletionsOpponent": 91, "passesIntercepted": 4, "passesInterceptedOpponent": 2, "passingTDs": 13, "passingTDsOpponent": 1, "penalties": 33, "penaltiesOpponent": 30, "penaltyYards": 364, "penaltyYardsOpponent": 253, "possessionTime": 6740, "possessionTimeOpponent": 7660, "puntReturns": 8, "puntReturnsOpponent": 1, "puntReturnTDs": 0, "puntReturnTDsOpponent": 0, "puntReturnYards": 79, "puntReturnYardsOpponent": 0, "rushingAttempts": 160, "rushingAttemptsOpponent": 124, "rushingTDs": 16, "rushingTDsOpponent": 0, "rushingYards": 992, "rushingYardsOpponent": 138, "sacks": 13, "sacksOpponent": 6, "tacklesForLoss": 43, "tacklesForLossOpponent": 14, "thirdDownConversions": 24, "thirdDownConversionsOpponent": 14, "thirdDowns": 43, "thirdDownsOpponent": 65, "totalYards": 2683, "totalYardsOpponent": 956, "turnovers": 3, "turnoversOpponent": 7}