{"firstDowns": 129, "firstDownsOpponent": 121, "fourthDownConversions": 5, "fourthDownConversionsOpponent": 5, "fourthDowns": 8, "fourthDownsOpponent": 13, "fumblesLost": 6, "fumblesLostOpponent": 5, "fumblesRecovered": 5, "fumblesRecoveredOpponent": 6, "games": 6, "interceptions": 5, "interceptionsOpponent": 10, "interceptionTDs": 0, "interceptionTDsOpponent": 0, "interceptionYards": 55, "interceptionYardsOpponent": 41, "kickReturns": 11, "kickReturnsOpponent": 15, "kickReturnTDs": 0, "kickReturnTDsOpponent": 0, "kickReturnYards": 213, "kickReturnYardsOpponent": 291, "netPassingYards": 1990, "netPassingYardsOpponent": 1246, "passAttempts": 247, "passAttemptsOpponent": 193, "passCompletions": 152, "passCompletionsOpponent": 113, "passesIntercepted": 10, "passesInterceptedOpponent": 5, "passingTDs": 18, "passingTDsOpponent": 8, "penalties": 40, "penaltiesOpponent": 50, "penaltyYards": 374, "penaltyYardsOpponent": 456, "possessionTime": 9897, "possessionTimeOpponent": 11719, "puntReturns": 5, "puntReturnsOpponent": 4, "puntReturnTDs": 0, "puntReturnTDsOpponent": 0, "puntReturnYards": 47, "puntReturnYardsOpponent": 23, "rushingAttempts": 158, "rushingAttemptsOpponent": 248, "rushingTDs": 8, "rushingTDsOpponent": 12, "rushingYards": 506, "rushingYardsOpponent": 1000, "sacks": 11, "sacksOpponent": 6, "tacklesForLoss": 41, "tacklesForLossOpponent": 31, "thirdDownConversions": 33, "thirdDownConversionsOpponent": 43, "thirdDowns": 78, "thirdDownsOpponent": 92, "totalYards": 2496, "totalYardsOpponent": 2246, "turnovers": 11, "turnoversOpponent": 15}