{"firstDowns": 114, "firstDownsOpponent": 79, "fourthDownConversions": 6, "fourthDownConversionsOpponent": 5, "fourthDowns": 11, "fourthDownsOpponent": 12, "fumblesLost": 5, "fumblesLostOpponent": 5, "fumblesRecovered": 5, "fumblesRecoveredOpponent": 5, "games": 5, "interceptions": 2, "interceptionsOpponent": 9, "interceptionTDs": 2, "interceptionTDsOpponent": 0, "interceptionYards": 246, "interceptionYardsOpponent": 0, "kickReturns": 10, "kickReturnsOpponent": 16, "kickReturnTDs": 0, "kickReturnTDsOpponent": 0, "kickReturnYards": 202, "kickReturnYardsOpponent": 252, "netPassingYards": 1069, "netPassingYardsOpponent": 1112, "passAttempts": 136, "passAttemptsOpponent": 164, "passCompletions": 84, "passCompletionsOpponent": 84, "passesIntercepted": 9, "passesInterceptedOpponent": 2, "passingTDs": 9, "passingTDsOpponent": 10, "penalties": 38, "penaltiesOpponent": 45, "penaltyYards": 377, "penaltyYardsOpponent": 375, "possessionTime": 9075, "possessionTimeOpponent": 8925, "puntReturns": 12, "puntReturnsOpponent": 4, "puntReturnTDs": 1, "puntReturnTDsOpponent": 0, "puntReturnYards": 120, "puntReturnYardsOpponent": 38, "rushingAttempts": 213, "rushingAttemptsOpponent": 161, "rushingTDs": 11, "rushingTDsOpponent": 4, "rushingYards": 1050, "rushingYardsOpponent": 454, "sacks": 7, "sacksOpponent": 6, "tacklesForLoss": 27, "tacklesForLossOpponent": 25, "thirdDownConversions": 32, "thirdDownConversionsOpponent": 24, "thirdDowns": 69, "thirdDownsOpponent": 71, "totalYards": 2119, "totalYardsOpponent": 1566, "turnovers": 7, "turnoversOpponent": 14}