{"firstDowns": 165, "firstDownsOpponent": 183, "fourthDownConversions": 14, "fourthDownConversionsOpponent": 7, "fourthDowns": 28, "fourthDownsOpponent": 10, "fumblesLost": 5, "fumblesLostOpponent": 6, "fumblesRecovered": 5, "fumblesRecoveredOpponent": 5, "games": 9, "interceptions": 13, "interceptionsOpponent": 7, "interceptionTDs": 1, "interceptionTDsOpponent": 0, "interceptionYards": 121, "interceptionYardsOpponent": 58, "kickReturns": 11, "kickReturnsOpponent": 21, "kickReturnTDs": 0, "kickReturnTDsOpponent": 0, "kickReturnYards": 188, "kickReturnYardsOpponent": 481, "netPassingYards": 1579, "netPassingYardsOpponent": 2413, "passAttempts": 267, "passAttemptsOpponent": 270, "passCompletions": 160, "passCompletionsOpponent": 179, "passesIntercepted": 7, "passesInterceptedOpponent": 13, "passingTDs": 12, "passingTDsOpponent": 23, "penalties": 47, "penaltiesOpponent": 58, "penaltyYards": 388, "penaltyYardsOpponent": 568, "possessionTime": 16846, "possessionTimeOpponent": 15554, "puntReturns": 11, "puntReturnsOpponent": 13, "puntReturnTDs": 1, "puntReturnTDsOpponent": 0, "puntReturnYards": 107, "puntReturnYardsOpponent": 122, "rushingAttempts": 327, "rushingAttemptsOpponent": 296, "rushingTDs": 7, "rushingTDsOpponent": 17, "rushingYards": 1276, "rushingYardsOpponent": 1308, "sacks": 18, "sacksOpponent": 30, "tacklesForLoss": 47, "tacklesForLossOpponent": 83, "thirdDownConversions": 40, "thirdDownConversionsOpponent": 48, "thirdDowns": 116, "thirdDownsOpponent": 109, "totalYards": 2855, "totalYardsOpponent": 3721, "turnovers": 18, "turnoversOpponent": 13}