{"firstDowns": 259, "firstDownsOpponent": 189, "fourthDownConversions": 18, "fourthDownConversionsOpponent": 7, "fourthDowns": 26, "fourthDownsOpponent": 10, "fumblesLost": 2, "fumblesLostOpponent": 4, "fumblesRecovered": 4, "fumblesRecoveredOpponent": 2, "games": 10, "interceptions": 12, "interceptionsOpponent": 9, "interceptionTDs": 1, "interceptionTDsOpponent": 4, "interceptionYards": 104, "interceptionYardsOpponent": 218, "kickReturns": 15, "kickReturnsOpponent": 12, "kickReturnTDs": 0, "kickReturnTDsOpponent": 0, "kickReturnYards": 288, "kickReturnYardsOpponent": 210, "netPassingYards": 3507, "netPassingYardsOpponent": 2015, "passAttempts": 481, "passAttemptsOpponent": 277, "passCompletions": 306, "passCompletionsOpponent": 184, "passesIntercepted": 9, "passesInterceptedOpponent": 12, "passingTDs": 24, "passingTDsOpponent": 15, "penalties": 74, "penaltiesOpponent": 50, "penaltyYards": 627, "penaltyYardsOpponent": 431, "possessionTime": 20293, "possessionTimeOpponent": 15707, "puntReturns": 13, "puntReturnsOpponent": 14, "puntReturnTDs": 0, "puntReturnTDsOpponent": 1, "puntReturnYards": 118, "puntReturnYardsOpponent": 99, "rushingAttempts": 306, "rushingAttemptsOpponent": 310, "rushingTDs": 16, "rushingTDsOpponent": 14, "rushingYards": 954, "rushingYardsOpponent": 1559, "sacks": 24, "sacksOpponent": 23, "tacklesForLoss": 60, "tacklesForLossOpponent": 53, "thirdDownConversions": 77, "thirdDownConversionsOpponent": 39, "thirdDowns": 158, "thirdDownsOpponent": 112, "totalYards": 4461, "totalYardsOpponent": 3574, "turnovers": 14, "turnoversOpponent": 13}