{"firstDowns": 36, "firstDownsOpponent": 10, "fourthDownConversions": 1, "fourthDownConversionsOpponent": 0, "fourthDowns": 1, "fourthDownsOpponent": 0, "fumblesLost": 0, "fumblesLostOpponent": 1, "fumblesRecovered": 1, "fumblesRecoveredOpponent": 0, "games": 1, "interceptions": 1, "interceptionsOpponent": 0, "interceptionTDsOpponent": 0, "interceptionYardsOpponent": 71, "kickReturns": 1, "kickReturnTDs": 0, "kickReturnYards": 35, "netPassingYards": 414, "netPassingYardsOpponent": 153, "passAttempts": 44, "passAttemptsOpponent": 24, "passCompletions": 33, "passCompletionsOpponent": 13, "passesInterceptedOpponent": 1, "passingTDs": 3, "passingTDsOpponent": 0, "penalties": 6, "penaltiesOpponent": 9, "penaltyYards": 52, "penaltyYardsOpponent": 65, "possessionTime": 1754, "possessionTimeOpponent": 1850, "puntReturns": 4, "puntReturnTDs": 1, "puntReturnYards": 69, "rushingAttempts": 46, "rushingAttemptsOpponent": 35, "rushingTDs": 5, "rushingTDsOpponent": 0, "rushingYards": 304, "rushingYardsOpponent": 74, "sacks": 1, "sacksOpponent": 2, "tacklesForLoss": 5, "tacklesForLossOpponent": 4, "thirdDownConversions": 9, "thirdDownConversionsOpponent": 1, "thirdDowns": 15, "thirdDownsOpponent": 14, "totalYards": 718, "totalYardsOpponent": 227, "turnovers": 1, "turnoversOpponent": 1}