{"firstDowns": 259, "firstDownsOpponent": 188, "fourthDownConversions": 8, "fourthDownConversionsOpponent": 11, "fourthDowns": 15, "fourthDownsOpponent": 22, "fumblesLost": 6, "fumblesLostOpponent": 7, "fumblesRecovered": 7, "fumblesRecoveredOpponent": 4, "games": 10, "interceptions": 9, "interceptionsOpponent": 5, "interceptionTDs": 0, "interceptionTDsOpponent": 0, "interceptionYards": 23, "interceptionYardsOpponent": 93, "kickReturns": 22, "kickReturnsOpponent": 8, "kickReturnTDs": 0, "kickReturnTDsOpponent": 0, "kickReturnYards": 451, "kickReturnYardsOpponent": 149, "netPassingYards": 2631, "netPassingYardsOpponent": 1882, "passAttempts": 321, "passAttemptsOpponent": 304, "passCompletions": 223, "passCompletionsOpponent": 168, "passesIntercepted": 5, "passesInterceptedOpponent": 9, "passingTDs": 26, "passingTDsOpponent": 7, "penalties": 64, "penaltiesOpponent": 63, "penaltyYards": 575, "penaltyYardsOpponent": 471, "possessionTime": 18227, "possessionTimeOpponent": 17768, "puntReturns": 17, "puntReturnsOpponent": 1, "puntReturnTDs": 0, "puntReturnTDsOpponent": 0, "puntReturnYards": 149, "puntReturnYardsOpponent": 5, "rushingAttempts": 388, "rushingAttemptsOpponent": 380, "rushingTDs": 19, "rushingTDsOpponent": 15, "rushingYards": 2079, "rushingYardsOpponent": 1420, "sacks": 30, "sacksOpponent": 12, "tacklesForLoss": 80, "tacklesForLossOpponent": 42, "thirdDownConversions": 57, "thirdDownConversionsOpponent": 54, "thirdDowns": 124, "thirdDownsOpponent": 151, "totalYards": 4710, "totalYardsOpponent": 3302, "turnovers": 15, "turnoversOpponent": 12}