{"firstDowns": 206, "firstDownsOpponent": 213, "fourthDownConversions": 7, "fourthDownConversionsOpponent": 9, "fourthDowns": 22, "fourthDownsOpponent": 19, "fumblesLost": 7, "fumblesLostOpponent": 5, "fumblesRecovered": 5, "fumblesRecoveredOpponent": 6, "games": 10, "interceptions": 7, "interceptionsOpponent": 7, "interceptionTDs": 1, "interceptionTDsOpponent": 0, "interceptionYards": 66, "interceptionYardsOpponent": 108, "kickReturns": 20, "kickReturnsOpponent": 24, "kickReturnTDs": 1, "kickReturnTDsOpponent": 0, "kickReturnYards": 464, "kickReturnYardsOpponent": 435, "netPassingYards": 2321, "netPassingYardsOpponent": 3091, "passAttempts": 350, "passAttemptsOpponent": 332, "passCompletions": 203, "passCompletionsOpponent": 216, "passesIntercepted": 7, "passesInterceptedOpponent": 7, "passingTDs": 20, "passingTDsOpponent": 29, "penalties": 63, "penaltiesOpponent": 84, "penaltyYards": 547, "penaltyYardsOpponent": 819, "possessionTime": 18115, "possessionTimeOpponent": 17885, "puntReturns": 22, "puntReturnsOpponent": 22, "puntReturnTDs": 1, "puntReturnTDsOpponent": 2, "puntReturnYards": 180, "puntReturnYardsOpponent": 409, "rushingAttempts": 375, "rushingAttemptsOpponent": 348, "rushingTDs": 8, "rushingTDsOpponent": 19, "rushingYards": 1530, "rushingYardsOpponent": 1501, "sacks": 15, "sacksOpponent": 19, "tacklesForLoss": 64, "tacklesForLossOpponent": 67, "thirdDownConversions": 62, "thirdDownConversionsOpponent": 51, "thirdDowns": 161, "thirdDownsOpponent": 131, "totalYards": 3851, "totalYardsOpponent": 4592, "turnovers": 14, "turnoversOpponent": 12}