{"firstDowns": 164, "firstDownsOpponent": 134, "fourthDownConversions": 8, "fourthDownConversionsOpponent": 10, "fourthDowns": 18, "fourthDownsOpponent": 19, "fumblesLost": 3, "fumblesLostOpponent": 2, "fumblesRecovered": 2, "fumblesRecoveredOpponent": 4, "games": 9, "interceptions": 14, "interceptionsOpponent": 8, "interceptionTDs": 0, "interceptionTDsOpponent": 0, "interceptionYards": 71, "interceptionYardsOpponent": 42, "kickReturns": 11, "kickReturnsOpponent": 20, "kickReturnTDs": 0, "kickReturnTDsOpponent": 1, "kickReturnYards": 230, "kickReturnYardsOpponent": 482, "netPassingYards": 1912, "netPassingYardsOpponent": 1575, "passAttempts": 280, "passAttemptsOpponent": 259, "passCompletions": 151, "passCompletionsOpponent": 128, "passesIntercepted": 8, "passesInterceptedOpponent": 14, "passingTDs": 17, "passingTDsOpponent": 10, "penalties": 48, "penaltiesOpponent": 61, "penaltyYards": 403, "penaltyYardsOpponent": 414, "possessionTime": 17879, "possessionTimeOpponent": 14521, "puntReturns": 16, "puntReturnsOpponent": 14, "puntReturnTDs": 0, "puntReturnTDsOpponent": 0, "puntReturnYards": 61, "puntReturnYardsOpponent": 80, "rushingAttempts": 313, "rushingAttemptsOpponent": 292, "rushingTDs": 6, "rushingTDsOpponent": 6, "rushingYards": 1354, "rushingYardsOpponent": 1210, "sacks": 15, "sacksOpponent": 17, "tacklesForLoss": 54, "tacklesForLossOpponent": 53, "thirdDownConversions": 43, "thirdDownConversionsOpponent": 31, "thirdDowns": 131, "thirdDownsOpponent": 130, "totalYards": 3266, "totalYardsOpponent": 2785, "turnovers": 17, "turnoversOpponent": 10}