[{"team1": "Virginia Tech", "team2": "Vanderbilt", "team1Elo": 1604, "team2Elo": 1284, "isHome": 0, "winner": 0, "week": 1}, {"team1": "Virginia Tech", "team2": "Marshall", "team1Elo": 1575, "team2Elo": 1406, "isHome": 1, "winner": 1, "week": 2}, {"team1": "Virginia Tech", "team2": "Old Dominion", "team1Elo": 1597, "team2Elo": 1397, "isHome": 0, "winner": 1, "week": 3}, {"team1": "Virginia Tech", "team2": "Rutgers", "team1Elo": 1626, "team2Elo": 1511, "isHome": 1, "winner": 0, "week": 4}, {"team1": "Virginia Tech", "team2": "Miami", "team1Elo": 1614, "team2Elo": 1837, "isHome": 0, "winner": 0, "week": 5}, {"team1": "Virginia Tech", "team2": "Stanford", "team1Elo": 1617, "team2Elo": 1288, "isHome": 0, "winner": 1, "week": 6}, {"team1": "Virginia Tech", "team2": "Boston College", "team1Elo": 1644, "team2Elo": 1448, "isHome": 1, "winner": 1, "week": 8}, {"team1": "Virginia Tech", "team2": "Georgia Tech", "team1Elo": 1674, "team2Elo": 1581, "isHome": 1, "winner": 1, "week": 9}, {"team1": "Virginia Tech", "team2": "Syracuse", "team1Elo": 1697, "team2Elo": 1360, "isHome": 0, "winner": 0, "week": 10}, {"team1": "Virginia Tech", "team2": "Clemson", "team1Elo": 1666, "team2Elo": 1819, "isHome": 1, "winner": 0, "week": 11}, {"team1": "Virginia Tech", "team2": "Duke", "team1Elo": 1658, "team2Elo": 1597, "isHome": 0, "winner": 0, "week": 13}, {"team1": "Virginia Tech", "team2": "Virginia", "team1Elo": 1656, "team2Elo": 1375, "isHome": 1, "winner": 1, "week": 14}, {"team1": "Virginia Tech", "team2": "Minnesota", "team1Elo": 1675, "team2Elo": 1646, "isHome": 1, "winner": 0, "week": 1}]